quantgpt_local_runner/__init__.py
quantgpt_local_runner/cli.py
quantgpt_local_runner/other_server.py
quantgpt_local_runner/server.py
quantgpt_local_runner-0.2.2.dist-info/METADATA
quantgpt_local_runner-0.2.2.dist-info/WHEEL
quantgpt_local_runner-0.2.2.dist-info/entry_points.txt
quantgpt_local_runner-0.2.2.dist-info/top_level.txt
quantgpt_local_runner-0.2.2.dist-info/RECORD
