Metadata-Version: 2.4
Name: quantgpt-local-runner
Version: 0.2.2
Summary: Local runner for QuantGPT with WebSocket support
Author-email: Bailey <bailey@justright.pl>
Classifier: Programming Language :: Python :: 3
Classifier: License :: OSI Approved :: MIT License
Classifier: Operating System :: OS Independent
Requires-Python: >=3.7
Requires-Dist: fastapi~=0.115.4
Requires-Dist: uvicorn~=0.31.0
Requires-Dist: typer~=0.11.0
Requires-Dist: termcolor~=2.4.0
